module_sum/__init__.py
module_sum/sum_elements.py
sum_elements_package-0.0.1.dist-info/LICENCE
sum_elements_package-0.0.1.dist-info/METADATA
sum_elements_package-0.0.1.dist-info/WHEEL
sum_elements_package-0.0.1.dist-info/top_level.txt
sum_elements_package-0.0.1.dist-info/RECORD
