Metadata-Version: 2.1
Name: sum_elements_package
Version: 0.0.1
Summary: A small example package
Author-email: Clémence Sutter <sutter.clemence@gmail.com>
Classifier: Development Status :: 3 - Alpha
Classifier: Intended Audience :: Developers
Classifier: License :: OSI Approved :: MIT License
Classifier: Programming Language :: Python :: 3
Classifier: Programming Language :: Python :: 3.7
Classifier: Programming Language :: Python :: 3.8
Classifier: Programming Language :: Python :: 3.9
License-File: LICENCE
